chrome_puppet-0.1.0.dist-info/licenses/LICENSE
core/__init__.py
core/config.py
core/orchestrator.py
core/system_info.py
core/browser/__init__.py
core/browser/base.py
core/browser/browser.py
core/browser/config.py
core/browser/driver_config.py
core/browser/exceptions.py
core/browser/types.py
core/browser/drivers/__init__.py
core/browser/drivers/chrome_driver.py
core/browser/features/__init__.py
core/browser/features/element.py
core/browser/features/navigation.py
core/browser/features/screenshot.py
core/sites/__init__.py
core/sites/base_site.py
core/sites/example_site.py
core/utils/__init__.py
core/utils/retry.py
core/utils/signal_handler.py
utils/__init__.py
utils/driver_manager.py
utils/utils.py
chrome_puppet-0.1.0.dist-info/METADATA
chrome_puppet-0.1.0.dist-info/WHEEL
chrome_puppet-0.1.0.dist-info/top_level.txt
chrome_puppet-0.1.0.dist-info/RECORD
